README.rst
setup.py
just_watch.egg-info/PKG-INFO
just_watch.egg-info/SOURCES.txt
just_watch.egg-info/dependency_links.txt
just_watch.egg-info/top_level.txt
justwatch/__init__.py
justwatch/manager.py
justwatch/objects.py
justwatch/observer.py