Metadata-Version: 1.1
Name: just-watch
Version: 1.0.0b1
Summary: Python utility to watch the file modification only.
Home-page: https://github.com/alice1017/JustWatch
Author: Hayato Tominaga
Author-email: takemehighermore@gmail.com
License: MIT License
Platform: UNKNOWN
Classifier: Development Status :: 4 - Beta
Classifier: Programming Language :: Python :: 2.7
Classifier: License :: OSI Approved :: MIT License
Classifier: Topic :: Utilities
